<?xml version="1.0" encoding="UTF-8"?>
<objects serializationModel="Studio.02.02.00">
	<object class="AudioFile" id="{6fd3e0db-292a-4613-8119-e5d9e4c8f1bd}">
		<property name="assetPath">
			<value>209840-EFX_SD_FS_Heavy_Creature_05 - Trimmed.wav</value>
		</property>
		<property name="frequencyInKHz">
			<value>96</value>
		</property>
		<property name="channelCount">
			<value>2</value>
		</property>
		<property name="length">
			<value>0.5</value>
		</property>
		<relationship name="masterAssetFolder">
			<destination>{dc32d93f-9386-4661-b92a-d4174f757eb9}</destination>
		</relationship>
	</object>
</objects>
